setup.py
mystarrail.egg-info/PKG-INFO
mystarrail.egg-info/SOURCES.txt
mystarrail.egg-info/dependency_links.txt
mystarrail.egg-info/requires.txt
mystarrail.egg-info/top_level.txt
starrail/Const.py
starrail/Effects.py
starrail/Relics.py
starrail/__init__.py