Metadata-Version: 2.1
Name: mystarrail
Version: 0.0.1
Summary: star rail lib
Author: jchensteve
Author-email: jchensteve@gmail.com
